Workbook

Sheet Dados
A1: Mês | B1: Leads | C1: Novos Clientes | D1: Clientes Perdidos | E1: Clientes Ativos | F1: Receita (MRR) | G1: Marketing (R$) | H1: Ticket Médio | I1: Burn Rate | J1: Caixa | K1: Usuários Ativos | L1: Convites | M1: Clientes por Indicação
A2: Mês 1 | B2: 185 | C2: 11 | D2: 3 | E2: =50+C2-D2 | F2: =E2*H2 | G2: 3100 | H2: 150 | I2: 15000 | J2: =250000-I2 | K2: 250 | L2: 40 | M2: 1
A3: Mês 2 | B3: 190 | C3: 11 | D3: 4 | E3: =E2+C3-D3 | F3: =E3*H3 | G3: 3000 | H3: 151 | I3: 15300 | J3: =J2-I3 | K3: 290 | L3: 48 | M3: 1
A4: Mês 3 | B4: 200 | C4: 12 | D4: 5 | E4: =E3+C4-D4 | F4: =E4*H4 | G4: 3100 | H4: 152 | I4: 15500 | J4: =J3-I4 | K4: 330 | L4: 55 | M4: 2
A5: Mês 4 | B5: 200 | C5: 10 | D5: 4 | E5: =E4+C5-D5 | F5: =E5*H5 | G5: 2600 | H5: 153 | I5: 15200 | J5: =J4-I5 | K5: 380 | L5: 65 | M5: 2
A6: Mês 5 | B6: 260 | C6: 18 | D6: 4 | E6: =E5+C6-D6 | F6: =E6*H6 | G6: 4000 | H6: 155 | I6: 14500 | J6: =J5-I6 | K6: 460 | L6: 90 | M6: 3
A7: Mês 6 | B7: 330 | C7: 24 | D7: 4 | E7: =E6+C7-D7 | F7: =E7*H7 | G7: 4600 | H7: 157 | I7: 13500 | J7: =J6-I7 | K7: 570 | L7: 120 | M7: 5
A8: Mês 7 | B8: 430 | C8: 33 | D8: 4 | E8: =E7+C8-D8 | F8: =E8*H8 | G8: 5400 | H8: 159 | I8: 12000 | J8: =J7-I8 | K8: 700 | L8: 160 | M8: 8
A9: Mês 8 | B9: 580 | C9: 46 | D9: 5 | E9: =E8+C9-D9 | F9: =E9*H9 | G9: 6400 | H9: 161 | I9: 10000 | J9: =J8-I9 | K9: 860 | L9: 210 | M9: 13
A10: Mês 9 | B10: 710 | C10: 60 | D10: 5 | E10: =E9+C10-D10 | F10: =E10*H10 | G10: 6900 | H10: 163 | I10: 8000 | J10: =J9-I10 | K10: 1060 | L10: 270 | M10: 19
A11: Mês 10 | B11: 820 | C11: 69 | D11: 5 | E11: =E10+C11-D11 | F11: =E11*H11 | G11: 6600 | H11: 165 | I11: 6000 | J11: =J10-I11 | K11: 1300 | L11: 340 | M11: 26
A12: Mês 11 | B12: 910 | C12: 77 | D12: 5 | E12: =E11+C12-D12 | F12: =E12*H12 | G12: 6000 | H12: 168 | I12: 4000 | J12: =J11-I12 | K12: 1580 | L12: 420 | M12: 34
A13: Mês 12 | B13: 1000 | C13: 80 | D13: 5 | E13: =E12+C13-D13 | F13: =E13*H13 | G13: 5200 | H13: 170 | I13: 2000 | J13: =J12-I13 | K13: 1900 | L13: 500 | M13: 40
A15: Caixa inicial (antes do Mês 1): R$ 250,000 · Clientes ativos iniciais: 50
A16: Preencha Leads, Novos/Perdidos Clientes, Marketing, Ticket Médio, Burn Rate, Usuários Ativos, Convites e Indicações — Clientes Ativos, Receita e Caixa se recalculam sozinhos.

Sheet Métricas
A1: Parâmetros
A2: Tamanho do mercado (clientes potenciais) | B2: 10000
A3: Limiar de % indicação p/ Tipping Point | B3: 0.3
A4: Limiar de LTV/CAC saudável (referência de mercado) | B4: 3
A6: Mês | B6: CAC | C6: Crescimento Receita (MoM) | D6: Conversão (Lead→Cliente) | E6: Churn | F6: Retenção | G6: LTV | H6: LTV/CAC | I6: Runway (meses) | J6: Crescimento de Usuários | K6: K-Factor | L6: Receita por Cliente | M6: Market Share
A7: =Dados!A2 | B7: =Dados!G2/Dados!C2 | D7: =Dados!C2/Dados!B2 | E7: =Dados!D2/Dados!E2 | F7: =1-E7 | G7: =Dados!H2*(1/E7) | H7: =G7/B7 | I7: =Dados!J2/Dados!I2 | K7: =Dados!M2/Dados!K2 | L7: =Dados!F2/Dados!E2 | M7: =Dados!E2/$B$2
A8: =Dados!A3 | B8: =Dados!G3/Dados!C3 | C8: =(Dados!F3-Dados!F2)/Dados!F2 | D8: =Dados!C3/Dados!B3 | E8: =Dados!D3/Dados!E3 | F8: =1-E8 | G8: =Dados!H3*(1/E8) | H8: =G8/B8 | I8: =Dados!J3/Dados!I3 | J8: =(Dados!K3-Dados!K2)/Dados!K2 | K8: =Dados!M3/Dados!K3 | L8: =Dados!F3/Dados!E3 | M8: =Dados!E3/$B$2
A9: =Dados!A4 | B9: =Dados!G4/Dados!C4 | C9: =(Dados!F4-Dados!F3)/Dados!F3 | D9: =Dados!C4/Dados!B4 | E9: =Dados!D4/Dados!E4 | F9: =1-E9 | G9: =Dados!H4*(1/E9) | H9: =G9/B9 | I9: =Dados!J4/Dados!I4 | J9: =(Dados!K4-Dados!K3)/Dados!K3 | K9: =Dados!M4/Dados!K4 | L9: =Dados!F4/Dados!E4 | M9: =Dados!E4/$B$2
A10: =Dados!A5 | B10: =Dados!G5/Dados!C5 | C10: =(Dados!F5-Dados!F4)/Dados!F4 | D10: =Dados!C5/Dados!B5 | E10: =Dados!D5/Dados!E5 | F10: =1-E10 | G10: =Dados!H5*(1/E10) | H10: =G10/B10 | I10: =Dados!J5/Dados!I5 | J10: =(Dados!K5-Dados!K4)/Dados!K4 | K10: =Dados!M5/Dados!K5 | L10: =Dados!F5/Dados!E5 | M10: =Dados!E5/$B$2
A11: =Dados!A6 | B11: =Dados!G6/Dados!C6 | C11: =(Dados!F6-Dados!F5)/Dados!F5 | D11: =Dados!C6/Dados!B6 | E11: =Dados!D6/Dados!E6 | F11: =1-E11 | G11: =Dados!H6*(1/E11) | H11: =G11/B11 | I11: =Dados!J6/Dados!I6 | J11: =(Dados!K6-Dados!K5)/Dados!K5 | K11: =Dados!M6/Dados!K6 | L11: =Dados!F6/Dados!E6 | M11: =Dados!E6/$B$2
A12: =Dados!A7 | B12: =Dados!G7/Dados!C7 | C12: =(Dados!F7-Dados!F6)/Dados!F6 | D12: =Dados!C7/Dados!B7 | E12: =Dados!D7/Dados!E7 | F12: =1-E12 | G12: =Dados!H7*(1/E12) | H12: =G12/B12 | I12: =Dados!J7/Dados!I7 | J12: =(Dados!K7-Dados!K6)/Dados!K6 | K12: =Dados!M7/Dados!K7 | L12: =Dados!F7/Dados!E7 | M12: =Dados!E7/$B$2
A13: =Dados!A8 | B13: =Dados!G8/Dados!C8 | C13: =(Dados!F8-Dados!F7)/Dados!F7 | D13: =Dados!C8/Dados!B8 | E13: =Dados!D8/Dados!E8 | F13: =1-E13 | G13: =Dados!H8*(1/E13) | H13: =G13/B13 | I13: =Dados!J8/Dados!I8 | J13: =(Dados!K8-Dados!K7)/Dados!K7 | K13: =Dados!M8/Dados!K8 | L13: =Dados!F8/Dados!E8 | M13: =Dados!E8/$B$2
A14: =Dados!A9 | B14: =Dados!G9/Dados!C9 | C14: =(Dados!F9-Dados!F8)/Dados!F8 | D14: =Dados!C9/Dados!B9 | E14: =Dados!D9/Dados!E9 | F14: =1-E14 | G14: =Dados!H9*(1/E14) | H14: =G14/B14 | I14: =Dados!J9/Dados!I9 | J14: =(Dados!K9-Dados!K8)/Dados!K8 | K14: =Dados!M9/Dados!K9 | L14: =Dados!F9/Dados!E9 | M14: =Dados!E9/$B$2
A15: =Dados!A10 | B15: =Dados!G10/Dados!C10 | C15: =(Dados!F10-Dados!F9)/Dados!F9 | D15: =Dados!C10/Dados!B10 | E15: =Dados!D10/Dados!E10 | F15: =1-E15 | G15: =Dados!H10*(1/E15) | H15: =G15/B15 | I15: =Dados!J10/Dados!I10 | J15: =(Dados!K10-Dados!K9)/Dados!K9 | K15: =Dados!M10/Dados!K10 | L15: =Dados!F10/Dados!E10 | M15: =Dados!E10/$B$2
A16: =Dados!A11 | B16: =Dados!G11/Dados!C11 | C16: =(Dados!F11-Dados!F10)/Dados!F10 | D16: =Dados!C11/Dados!B11 | E16: =Dados!D11/Dados!E11 | F16: =1-E16 | G16: =Dados!H11*(1/E16) | H16: =G16/B16 | I16: =Dados!J11/Dados!I11 | J16: =(Dados!K11-Dados!K10)/Dados!K10 | K16: =Dados!M11/Dados!K11 | L16: =Dados!F11/Dados!E11 | M16: =Dados!E11/$B$2
A17: =Dados!A12 | B17: =Dados!G12/Dados!C12 | C17: =(Dados!F12-Dados!F11)/Dados!F11 | D17: =Dados!C12/Dados!B12 | E17: =Dados!D12/Dados!E12 | F17: =1-E17 | G17: =Dados!H12*(1/E17) | H17: =G17/B17 | I17: =Dados!J12/Dados!I12 | J17: =(Dados!K12-Dados!K11)/Dados!K11 | K17: =Dados!M12/Dados!K12 | L17: =Dados!F12/Dados!E12 | M17: =Dados!E12/$B$2
A18: =Dados!A13 | B18: =Dados!G13/Dados!C13 | C18: =(Dados!F13-Dados!F12)/Dados!F12 | D18: =Dados!C13/Dados!B13 | E18: =Dados!D13/Dados!E13 | F18: =1-E18 | G18: =Dados!H13*(1/E18) | H18: =G18/B18 | I18: =Dados!J13/Dados!I13 | J18: =(Dados!K13-Dados!K12)/Dados!K12 | K18: =Dados!M13/Dados!K13 | L18: =Dados!F13/Dados!E13 | M18: =Dados!E13/$B$2

Sheet Pontos de Virada
A1: Estes 5 conceitos não são métricas novas — são leituras (padrões) em cima das métricas já calculadas na aba "Métricas".
A2: A tabela abaixo sinaliza automaticamente candidatos a Inflection Point, Tipping Point e Turning Point,
A3: e traz um checklist manual para Milestones e uma coluna livre para registrar o Catalisador de cada mudança.
A5: Mês | B5: Crescimento Receita | C5: Aceleração do Crescimento (Δ crescimento) | D5: Sinal: Inflection Point | E5: % Novos Clientes por Indicação | F5: Sinal: Tipping Point | G5: Sinal: Turning Point (churn) | H5: Catalisador (evento do mês)
A6: =Dados!A2 | B6: =Métricas!C7 | E6: =Dados!M2/Dados!C2 | F6: =IF(E6>=Métricas!$B$3,"🔥 Tipping Point (indicação vira canal dominante)","")
A7: =Dados!A3 | B7: =Métricas!C8 | E7: =Dados!M3/Dados!C3 | F7: =IF(E7>=Métricas!$B$3,"🔥 Tipping Point (indicação vira canal dominante)","")
A8: =Dados!A4 | B8: =Métricas!C9 | C8: =Métricas!C9-Métricas!C8 | D8: =IF(AND(C8>0,C7<=0),"⬆ Possível Inflection Point","") | E8: =Dados!M4/Dados!C4 | F8: =IF(E8>=Métricas!$B$3,"🔥 Tipping Point (indicação vira canal dominante)","") | G8: =IF(AND(Métricas!E9<Métricas!E8,Métricas!E8>Métricas!E7),"↩ Turning Point (churn começou a cair)","")
A9: =Dados!A5 | B9: =Métricas!C10 | C9: =Métricas!C10-Métricas!C9 | D9: =IF(AND(C9>0,C8<=0),"⬆ Possível Inflection Point","") | E9: =Dados!M5/Dados!C5 | F9: =IF(E9>=Métricas!$B$3,"🔥 Tipping Point (indicação vira canal dominante)","") | G9: =IF(AND(Métricas!E10<Métricas!E9,Métricas!E9>Métricas!E8),"↩ Turning Point (churn começou a cair)","") | H9: Melhoria no onboarding/suporte (reduz cancelamentos) → catalisador do Turning Point ao lado
A10: =Dados!A6 | B10: =Métricas!C11 | C10: =Métricas!C11-Métricas!C10 | D10: =IF(AND(C10>0,C9<=0),"⬆ Possível Inflection Point","") | E10: =Dados!M6/Dados!C6 | F10: =IF(E10>=Métricas!$B$3,"🔥 Tipping Point (indicação vira canal dominante)","") | G10: =IF(AND(Métricas!E11<Métricas!E10,Métricas!E10>Métricas!E9),"↩ Turning Point (churn começou a cair)","") | H10: Início de campanha em redes sociais/mídia paga → catalisador do Inflection Point ao lado
A11: =Dados!A7 | B11: =Métricas!C12 | C11: =Métricas!C12-Métricas!C11 | D11: =IF(AND(C11>0,C10<=0),"⬆ Possível Inflection Point","") | E11: =Dados!M7/Dados!C7 | F11: =IF(E11>=Métricas!$B$3,"🔥 Tipping Point (indicação vira canal dominante)","") | G11: =IF(AND(Métricas!E12<Métricas!E11,Métricas!E11>Métricas!E10),"↩ Turning Point (churn começou a cair)","") | H11: Parceria com evento/casa noturna
A12: =Dados!A8 | B12: =Métricas!C13 | C12: =Métricas!C13-Métricas!C12 | D12: =IF(AND(C12>0,C11<=0),"⬆ Possível Inflection Point","") | E12: =Dados!M8/Dados!C8 | F12: =IF(E12>=Métricas!$B$3,"🔥 Tipping Point (indicação vira canal dominante)","") | G12: =IF(AND(Métricas!E13<Métricas!E12,Métricas!E12>Métricas!E11),"↩ Turning Point (churn começou a cair)","")
A13: =Dados!A9 | B13: =Métricas!C14 | C13: =Métricas!C14-Métricas!C13 | D13: =IF(AND(C13>0,C12<=0),"⬆ Possível Inflection Point","") | E13: =Dados!M9/Dados!C9 | F13: =IF(E13>=Métricas!$B$3,"🔥 Tipping Point (indicação vira canal dominante)","") | G13: =IF(AND(Métricas!E14<Métricas!E13,Métricas!E13>Métricas!E12),"↩ Turning Point (churn começou a cair)","") | H13: Lançamento do programa de indicação (referral)
A14: =Dados!A10 | B14: =Métricas!C15 | C14: =Métricas!C15-Métricas!C14 | D14: =IF(AND(C14>0,C13<=0),"⬆ Possível Inflection Point","") | E14: =Dados!M10/Dados!C10 | F14: =IF(E14>=Métricas!$B$3,"🔥 Tipping Point (indicação vira canal dominante)","") | G14: =IF(AND(Métricas!E15<Métricas!E14,Métricas!E14>Métricas!E13),"↩ Turning Point (churn começou a cair)","") | H14: Matéria em imprensa especializada → reforça o Tipping Point ao lado
A15: =Dados!A11 | B15: =Métricas!C16 | C15: =Métricas!C16-Métricas!C15 | D15: =IF(AND(C15>0,C14<=0),"⬆ Possível Inflection Point","") | E15: =Dados!M11/Dados!C11 | F15: =IF(E15>=Métricas!$B$3,"🔥 Tipping Point (indicação vira canal dominante)","") | G15: =IF(AND(Métricas!E16<Métricas!E15,Métricas!E15>Métricas!E14),"↩ Turning Point (churn começou a cair)","")
A16: =Dados!A12 | B16: =Métricas!C17 | C16: =Métricas!C17-Métricas!C16 | D16: =IF(AND(C16>0,C15<=0),"⬆ Possível Inflection Point","") | E16: =Dados!M12/Dados!C12 | F16: =IF(E16>=Métricas!$B$3,"🔥 Tipping Point (indicação vira canal dominante)","") | G16: =IF(AND(Métricas!E17<Métricas!E16,Métricas!E16>Métricas!E15),"↩ Turning Point (churn começou a cair)","")
A17: =Dados!A13 | B17: =Métricas!C18 | C17: =Métricas!C18-Métricas!C17 | D17: =IF(AND(C17>0,C16<=0),"⬆ Possível Inflection Point","") | E17: =Dados!M13/Dados!C13 | F17: =IF(E17>=Métricas!$B$3,"🔥 Tipping Point (indicação vira canal dominante)","") | G17: =IF(AND(Métricas!E18<Métricas!E17,Métricas!E17>Métricas!E16),"↩ Turning Point (churn começou a cair)","") | H17: Ajuste de preço/upsell no ticket médio
A20: Milestones
A21: Milestone | B21: Métrica-alvo | C21: Valor-alvo | D21: Mês em que foi atingido
A22: Primeiros 100 clientes ativos | B22: Clientes Ativos | C22: 100 | D22: =IFERROR(INDEX(Dados!$A$2:$A$13,MATCH(TRUE,INDEX(Dados!$E$2:$E$13>=C22,0),0)),"ainda não")
A23: MRR de R$ 50.000 | B23: Receita (MRR) | C23: 50000 | D23: =IFERROR(INDEX(Dados!$A$2:$A$13,MATCH(TRUE,INDEX(Dados!$F$2:$F$13>=C23,0),0)),"ainda não")
A24: Runway acima de 18 meses (sustentado) | B24: Runway | C24: 18 | D24: =IFERROR(INDEX(Métricas!$A$7:$A$18,MATCH(TRUE,INDEX(Métricas!$I$7:$I$18>=C24,0),0)),"ainda não")
A25: Burn rate abaixo de R$ 3.000/mês (quase break-even) | B25: Burn Rate | C25: 3000 | D25: =IFERROR(INDEX(Dados!$A$2:$A$13,MATCH(TRUE,INDEX(Dados!$I$2:$I$13<=C25,0),0)),"ainda não")
A27: Como usar esta aba:
A28: • Inflection Point = a taxa de crescimento (não a receita) volta a acelerar depois de estar estagnada/caindo — olhe a coluna "Aceleração do Crescimento".
A29: • Tipping Point = o canal orgânico/indicação passa a puxar a maior parte dos novos clientes (aqui, ≥30% — ajuste em Métricas!B3) — sinal de que a adoção passou a se autoalimentar.
A30: • Turning Point = qualquer métrica que estava piorando reverte de direção; o exemplo aqui é o churn, mas o mesmo padrão (pico seguido de queda) vale para CAC, burn rate etc.
A31: • Milestone = uma meta pré-definida, batida ou não — não exige reversão de tendência, só comparação com um alvo (tabela acima).
A32: • Catalyst = não é calculado a partir de números; é o evento real (campanha, parceria, lançamento de feature, imprensa) que você registra manualmente e depois cruza com os sinais acima para entender o que causou a virada.
